Db4eSystemd/__init__.py
db4e_systemd-1.0.1.dist-info/LICENSE
db4e_systemd-1.0.1.dist-info/METADATA
db4e_systemd-1.0.1.dist-info/WHEEL
db4e_systemd-1.0.1.dist-info/top_level.txt
db4e_systemd-1.0.1.dist-info/RECORD
