Metadata-Version: 2.1
Name: db4e-systemd
Version: 1.0.1
Summary: A lightweight systemctl wrapper for Python
Home-page: https://github.com/NadimGhaznavi/db4e-systemd
Author: Nadim-Daniel Ghaznavi
Classifier: Programming Language :: Python :: 3
Classifier: License :: OSI Approved :: GNU General Public License v3 (GPLv3)
Classifier: Operating System :: POSIX :: Linux
Requires-Python: >=3.7
License-File: LICENSE
